{
  "BASE_CHUNK_SIZE": 2097152,
  "MIN_CHUNK_SIZE": 262144,
  "MAX_CHUNK_SIZE": 8388608,
  "CHUNK_IO_SIZE": 65536,
  "REQUEST_TIMEOUT_SECONDS": 60,
  "RETRY_ATTEMPTS": 3,
  "RETRY_DELAY_SECONDS": 2,
  "WEIGHT_REBALANCE_INTERVAL_SECONDS": 5,
  "MIN_INTERFACE_SPEED_THRESHOLD": 0.05,
  "SLOW_INTERFACE_GRACE_PERIOD": 10,
  "DISCONNECT_DETECTION_TIMEOUT": 3,
  "RETRY_SAME_INTERFACE_COOLDOWN": 15,
  "MAX_CONSECUTIVE_FAILURES": 3,
  "SPEED_SAMPLE_INTERVAL": 0.1,
  "SPEED_WINDOW_SECONDS": 2,
  "SPEEDTEST_URL": "https://speed.cloudflare.com/__down?bytes=1000000",
  "SPEEDTEST_TIMEOUT": 20,
  "HTTP_HANDLER_SIZE_THRESHOLD": 52428800,
  "DEFAULT_DOWNLOAD_PATH": "C:\\Downloads",
  "THEME_MODE": "light"
}